ContrailOnlineCAService-0.4.0.dist-info/DESCRIPTION.rst
ContrailOnlineCAService-0.4.0.dist-info/METADATA
ContrailOnlineCAService-0.4.0.dist-info/RECORD
ContrailOnlineCAService-0.4.0.dist-info/WHEEL
ContrailOnlineCAService-0.4.0.dist-info/metadata.json
ContrailOnlineCAService-0.4.0.dist-info/top_level.txt
contrail/__init__.py
contrail/security/__init__.py
contrail/security/onlineca/__init__.py
contrail/security/onlineca/server/LICENSE
contrail/security/onlineca/server/__init__.py
contrail/security/onlineca/server/factory.py
contrail/security/onlineca/server/impl.py
contrail/security/onlineca/server/interfaces.py
contrail/security/onlineca/server/openssl_utils.py
contrail/security/onlineca/server/test/README
contrail/security/onlineca/server/test/__init__.py
contrail/security/onlineca/server/test/client_register.ini
contrail/security/onlineca/server/test/httpbasicauth-server.ini
contrail/security/onlineca/server/test/localhost.crt
contrail/security/onlineca/server/test/localhost.key
contrail/security/onlineca/server/test/localhost.pem
contrail/security/onlineca/server/test/onlineca-server-with-httpbasicauth.ini
contrail/security/onlineca/server/test/onlineca-server.ini
contrail/security/onlineca/server/test/onlineca_server.py
contrail/security/onlineca/server/test/onlineca_server_with_httpbasicauth.py
contrail/security/onlineca/server/test/server_utils.py
contrail/security/onlineca/server/test/test_client_register.py
contrail/security/onlineca/server/test/test_httpbasicauth.py
contrail/security/onlineca/server/test/ca/08bd99c7.0
contrail/security/onlineca/server/test/ca/530f7122.0
contrail/security/onlineca/server/test/ca/7ed47087.0
contrail/security/onlineca/server/test/ca/98ef0ee5.0
contrail/security/onlineca/server/test/ca/ade0138a.0
contrail/security/onlineca/server/test/ca/ffc3d59b.0
contrail/security/onlineca/server/test/ca/test-ca.crt
contrail/security/onlineca/server/test/ca/test-ca.key
contrail/security/onlineca/server/test/repoze_eg/__init__.py
contrail/security/onlineca/server/test/repoze_eg/onlineca-server-with-httpbasicauth.ini
contrail/security/onlineca/server/test/repoze_eg/onlineca_server_with_httpbasicauth.py
contrail/security/onlineca/server/test/repoze_eg/passwd
