Metadata-Version: 2.0
Name: ContrailOnlineCAService
Version: 0.4.0
Summary: Certificate Authority Web Service
Home-page: https://github.com/cedadev/online_ca_service
Author: Philip Kershaw
Author-email: Philip.Kershaw@stfc.ac.uk
License: BSD - See LICENSE file in contrail.security.onlineca.server
Platform: POSIX
Platform: Linux
Platform: Windows
Classifier: Development Status :: 5 - Production/Stable
Classifier: Environment :: Console
Classifier: Environment :: Web Environment
Classifier: Intended Audience :: End Users/Desktop
Classifier: Intended Audience :: Developers
Classifier: Intended Audience :: System Administrators
Classifier: Intended Audience :: Science/Research
Classifier: License :: OSI Approved :: BSD License
Classifier: Natural Language :: English
Classifier: Operating System :: Microsoft :: Windows
Classifier: Operating System :: POSIX :: Linux
Classifier: Programming Language :: Python
Classifier: Programming Language :: Python :: 3
Classifier: Topic :: Security
Classifier: Topic :: Internet
Classifier: Topic :: Scientific/Engineering
Classifier: Topic :: System :: Distributed Computing
Classifier: Topic :: System :: Systems Administration :: Authentication/Directory
Classifier: Topic :: Software Development :: Libraries :: Python Modules
Requires-Dist: ContrailCA
Requires-Dist: PasteScript
Requires-Dist: WebOb
Provides-Extra: repoze.who
Requires-Dist: repoze.who; extra == 'repoze.who'
Provides-Extra: testserver
Requires-Dist: waitress; extra == 'testserver'
